LICENSE
MANIFEST.in
README.md
setup.py
etc/example.yaml
etc/init.d/tinman
etc/sysconfig/tinman
tinman/__init__.py
tinman/application.py
tinman/config.py
tinman/controller.py
tinman/couchdb.py
tinman/example.py
tinman/exceptions.py
tinman/mapping.py
tinman/model.py
tinman/process.py
tinman/serializers.py
tinman/session.py
tinman/utils.py
tinman.egg-info/PKG-INFO
tinman.egg-info/SOURCES.txt
tinman.egg-info/dependency_links.txt
tinman.egg-info/entry_points.txt
tinman.egg-info/requires.txt
tinman.egg-info/top_level.txt
tinman.egg-info/zip-safe
tinman/auth/__init__.py
tinman/auth/basic.py
tinman/auth/digest.py
tinman/auth/ldapauth.py
tinman/auth/mixins.py
tinman/decorators/__init__.py
tinman/decorators/authentication.py
tinman/decorators/memoize.py
tinman/decorators/whitelist.py
tinman/handlers/__init__.py
tinman/handlers/base.py
tinman/handlers/heapy.py
tinman/handlers/mixins.py
tinman/handlers/rabbitmq.py
tinman/handlers/redis_handlers.py
tinman/handlers/session.py
tinman/loaders/__init__.py
tinman/loaders/couchdb.py
tinman/utilities/__init__.py
tinman/utilities/heapy_report.py
tinman/utilities/initialize.py