Metadata-Version: 1.1
Name: tinman
Version: 0.10.0p3
Summary: Tornado application wrapper and toolset for Tornado development
Home-page: http://github.com/gmr/tinman
Author: Gavin M. Roy
Author-email: gavinmroy@gmail.com
License: Copyright (c) 2011-2012, MeetMe
